netwatch/__init__.py
netwatch/db.py
netwatch/graph.py
netwatch/monitor.py
netwatch/tui.py
netwatch/utils.py
netwatchpy-1.2.3.dist-info/licenses/LICENSE
netwatchpy-1.2.3.dist-info/METADATA
netwatchpy-1.2.3.dist-info/WHEEL
netwatchpy-1.2.3.dist-info/entry_points.txt
netwatchpy-1.2.3.dist-info/top_level.txt
netwatchpy-1.2.3.dist-info/RECORD
