Metadata-Version: 2.4
Name: netwatchpy
Version: 1.2.3
Summary: A TUI network usage monitor.
Author-email: Pranav Kishan <ty.pranavkishan7905@gmail.com>
License: MIT
Project-URL: Documentation, https://destroyer795.github.io/Netwatchpy-package
Project-URL: Homepage, https://github.com/Destroyer795/Netwatchpy-package
Project-URL: Issues, https://github.com/Destroyer795/Netwatchpy-package/issues
Requires-Python: >=3.8
License-File: LICENSE
Requires-Dist: textual
Requires-Dist: psutil
Requires-Dist: desktop-notifier
Requires-Dist: platformdirs
Dynamic: license-file
